winpwn/__init__.py
winpwn/context.py
winpwn/dbg.py
winpwn/misc.py
winpwn/var.py
winpwn/win.py
winpwn/winpwn.py
wepwn-0.0.1.dist-info/METADATA
wepwn-0.0.1.dist-info/WHEEL
wepwn-0.0.1.dist-info/top_level.txt
wepwn-0.0.1.dist-info/RECORD
